LICENSE
README.md
pyproject.toml
setup.py
gaia_source/__init__.py
gaia_source/constants.py
gaia_source/datatypes.py
gaia_source/factory.py
gaia_source/utils.py
gaia_source.egg-info/PKG-INFO
gaia_source.egg-info/SOURCES.txt
gaia_source.egg-info/dependency_links.txt
gaia_source.egg-info/entry_points.txt
gaia_source.egg-info/not-zip-safe
gaia_source.egg-info/requires.txt
gaia_source.egg-info/top_level.txt