Metadata-Version: 2.1
Name: gaia-source
Version: 0.0.1
Summary: A utility to manage gaia_source/csv
Home-page: https://github.com/jbcurtin/gaia_source
Author: Joseph Curtin <josephbcurtin@gmail.com>
Author-email: josephbcurtin@gmail.com
License: MIT License
Platform: UNKNOWN
Classifier: Operating System :: OS Independent
Classifier: Programming Language :: Python
Classifier: Programming Language :: Python :: 3
Classifier: Programming Language :: Python :: 3 :: Only
Classifier: Programming Language :: Python :: 3.9
Requires-Python: >=3.9
License-File: LICENSE
